epp/__init__.py
epp/core.py
epp/errors.py
epp/extras.py
epp/parsers.py
epparsers-0.4.1.dist-info/DESCRIPTION.rst
epparsers-0.4.1.dist-info/METADATA
epparsers-0.4.1.dist-info/RECORD
epparsers-0.4.1.dist-info/WHEEL
epparsers-0.4.1.dist-info/metadata.json
epparsers-0.4.1.dist-info/top_level.txt
