Metadata-Version: 2.0
Name: epparsers
Version: 0.4.1
Summary: Effectful pythonic parsers
Home-page: https://github.com/mpevnev/epp
Author: Michail Pevnev
Author-email: mpevnev@gmail.com
License: LGPL-3
Keywords: parser parsers
Platform: UNKNOWN
Classifier: Development Status :: 3 - Alpha
Classifier: Intended Audience :: Developers
Classifier: License :: OSI Approved :: GNU Lesser General Public License v3 (LGPLv3)
